{
	"info": {
		"_postman_id": "afb26ec7-b903-481b-9239-b6b96d35d1cf",
		"name": "员工管理",
		"schema": "https://schema.getpostman.com/json/collection/v2.1.0/collection.json",
		"_exporter_id": "18201689"
	},
	"item": [
		{
			"name": "修改员工",
			"request": {
				"method": "PUT",
				"header": [],
				"body": {
					"mode": "raw",
					"raw": "{\r\n    \"name\":\"11\",\r\n    \"salary\":123.3,\r\n    \"age\":20\r\n}",
					"options": {
						"raw": {
							"language": "json"
						}
					}
				},
				"url": {
					"raw": "http://localhost:3000/employee/651fdfe23504c86011e06e76",
					"protocol": "http",
					"host": [
						"localhost"
					],
					"port": "3000",
					"path": [
						"employee",
						"651fdfe23504c86011e06e76"
					]
				}
			},
			"response": []
		},
		{
			"name": "查看所有员工",
			"request": {
				"method": "GET",
				"header": [],
				"url": {
					"raw": "http://localhost:3000/employee",
					"protocol": "http",
					"host": [
						"localhost"
					],
					"port": "3000",
					"path": [
						"employee"
					]
				}
			},
			"response": []
		},
		{
			"name": "添加员工",
			"request": {
				"method": "POST",
				"header": [],
				"body": {
					"mode": "raw",
					"raw": "{\r\n    \"name\":\"11\",\r\n    \"salary\":123.3,\r\n    \"age\":18\r\n}",
					"options": {
						"raw": {
							"language": "json"
						}
					}
				},
				"url": {
					"raw": "http://localhost:3000/employee",
					"protocol": "http",
					"host": [
						"localhost"
					],
					"port": "3000",
					"path": [
						"employee"
					]
				}
			},
			"response": []
		},
		{
			"name": "删除员工",
			"request": {
				"method": "DELETE",
				"header": [],
				"url": {
					"raw": "http://localhost:3000/employee/651fdfe23504c86011e06e76",
					"protocol": "http",
					"host": [
						"localhost"
					],
					"port": "3000",
					"path": [
						"employee",
						"651fdfe23504c86011e06e76"
					]
				}
			},
			"response": []
		}
	]
}